{
  "schema_version": "metro_timetable.v1",
  "line": "10号线",
  "station": "团结湖",
  "direction": "团结湖站-呼家楼站方向",
  "service_day": "weekend",
  "source_image": "data/metro/images/d_file_station_xltcx_line10_2025-01-24_10号线-团结湖站-呼家楼站方向-双休日.jpg_1",
  "source_url": "https://www.bjsubway.com/d/file/station/xltcx/line10/2025-01-24/10号线-团结湖站-呼家楼站方向-双休日.jpg?=1",
  "read_by": "vision-model",
  "read_at": "2026-05-11T07:20:00.000+08:00",
  "confidence": "high",
  "times": [
    {
      "time": "05:12"
    },
    {
      "time": "05:20"
    },
    {
      "time": "05:28"
    },
    {
      "time": "05:35"
    },
    {
      "time": "05:42"
    },
    {
      "time": "05:49"
    },
    {
      "time": "05:56"
    },
    {
      "time": "06:03"
    },
    {
      "time": "06:10"
    },
    {
      "time": "06:17"
    },
    {
      "time": "06:24"
    },
    {
      "time": "06:31"
    },
    {
      "time": "06:38"
    },
    {
      "time": "06:45"
    },
    {
      "time": "06:51"
    },
    {
      "time": "06:57"
    },
    {
      "time": "07:05"
    },
    {
      "time": "07:12"
    },
    {
      "time": "07:19"
    },
    {
      "time": "07:26"
    },
    {
      "time": "07:33"
    },
    {
      "time": "07:40"
    },
    {
      "time": "07:47"
    },
    {
      "time": "07:54"
    },
    {
      "time": "08:01"
    },
    {
      "time": "08:08"
    },
    {
      "time": "08:15"
    },
    {
      "time": "08:22"
    },
    {
      "time": "08:29"
    },
    {
      "time": "08:36"
    },
    {
      "time": "08:43"
    },
    {
      "time": "08:50"
    },
    {
      "time": "08:56"
    },
    {
      "time": "09:03"
    },
    {
      "time": "09:10"
    },
    {
      "time": "09:17"
    },
    {
      "time": "09:24"
    },
    {
      "time": "09:31"
    },
    {
      "time": "09:38"
    },
    {
      "time": "09:45"
    },
    {
      "time": "09:52"
    },
    {
      "time": "09:59"
    },
    {
      "time": "10:06"
    },
    {
      "time": "10:13"
    },
    {
      "time": "10:20"
    },
    {
      "time": "10:27"
    },
    {
      "time": "10:34"
    },
    {
      "time": "10:41"
    },
    {
      "time": "10:48"
    },
    {
      "time": "10:55"
    },
    {
      "time": "11:02"
    },
    {
      "time": "11:09"
    },
    {
      "time": "11:15"
    },
    {
      "time": "11:22"
    },
    {
      "time": "11:29"
    },
    {
      "time": "11:36"
    },
    {
      "time": "11:43"
    },
    {
      "time": "11:50"
    },
    {
      "time": "11:57"
    },
    {
      "time": "12:04"
    },
    {
      "time": "12:11"
    },
    {
      "time": "12:18"
    },
    {
      "time": "12:25"
    },
    {
      "time": "12:32"
    },
    {
      "time": "12:39"
    },
    {
      "time": "12:46"
    },
    {
      "time": "12:53"
    },
    {
      "time": "13:00"
    },
    {
      "time": "13:07"
    },
    {
      "time": "13:14"
    },
    {
      "time": "13:21"
    },
    {
      "time": "13:28"
    },
    {
      "time": "13:34"
    },
    {
      "time": "13:41"
    },
    {
      "time": "13:48"
    },
    {
      "time": "13:55"
    },
    {
      "time": "14:02"
    },
    {
      "time": "14:09"
    },
    {
      "time": "14:16"
    },
    {
      "time": "14:23"
    },
    {
      "time": "14:30"
    },
    {
      "time": "14:37"
    },
    {
      "time": "14:44"
    },
    {
      "time": "14:51"
    },
    {
      "time": "14:58"
    },
    {
      "time": "15:05"
    },
    {
      "time": "15:12"
    },
    {
      "time": "15:19"
    },
    {
      "time": "15:22"
    },
    {
      "time": "15:26"
    },
    {
      "time": "15:33"
    },
    {
      "time": "15:40"
    },
    {
      "time": "15:42"
    },
    {
      "time": "15:47"
    },
    {
      "time": "15:53"
    },
    {
      "time": "15:57"
    },
    {
      "time": "16:03"
    },
    {
      "time": "16:07"
    },
    {
      "time": "16:14"
    },
    {
      "time": "16:18"
    },
    {
      "time": "16:24"
    },
    {
      "time": "16:28"
    },
    {
      "time": "16:32"
    },
    {
      "time": "16:38"
    },
    {
      "time": "16:42"
    },
    {
      "time": "16:49"
    },
    {
      "time": "16:54"
    },
    {
      "time": "16:59"
    },
    {
      "time": "17:04"
    },
    {
      "time": "17:09"
    },
    {
      "time": "17:14"
    },
    {
      "time": "17:19"
    },
    {
      "time": "17:24"
    },
    {
      "time": "17:29"
    },
    {
      "time": "17:34"
    },
    {
      "time": "17:39"
    },
    {
      "time": "17:44"
    },
    {
      "time": "17:49"
    },
    {
      "time": "17:54"
    },
    {
      "time": "17:59"
    },
    {
      "time": "18:04"
    },
    {
      "time": "18:09"
    },
    {
      "time": "18:13"
    },
    {
      "time": "18:18"
    },
    {
      "time": "18:23"
    },
    {
      "time": "18:28"
    },
    {
      "time": "18:33"
    },
    {
      "time": "18:38"
    },
    {
      "time": "18:43"
    },
    {
      "time": "18:48"
    },
    {
      "time": "18:53"
    },
    {
      "time": "18:58"
    },
    {
      "time": "19:03"
    },
    {
      "time": "19:10"
    },
    {
      "time": "19:17"
    },
    {
      "time": "19:20"
    },
    {
      "time": "19:24"
    },
    {
      "time": "19:31"
    },
    {
      "time": "19:34"
    },
    {
      "time": "19:38"
    },
    {
      "time": "19:45"
    },
    {
      "time": "19:52"
    },
    {
      "time": "19:59"
    },
    {
      "time": "20:05"
    },
    {
      "time": "20:12"
    },
    {
      "time": "20:19"
    },
    {
      "time": "20:26"
    },
    {
      "time": "20:33"
    },
    {
      "time": "20:40"
    },
    {
      "time": "20:47"
    },
    {
      "time": "20:54"
    },
    {
      "time": "21:01"
    },
    {
      "time": "21:08"
    },
    {
      "time": "21:15"
    },
    {
      "time": "21:22"
    },
    {
      "time": "21:29"
    },
    {
      "time": "21:36"
    },
    {
      "time": "21:43"
    },
    {
      "time": "21:50"
    },
    {
      "time": "21:57"
    },
    {
      "time": "22:04"
    },
    {
      "time": "22:11"
    },
    {
      "time": "22:18"
    },
    {
      "time": "22:24"
    },
    {
      "time": "22:31"
    },
    {
      "time": "22:38"
    },
    {
      "time": "22:45"
    },
    {
      "time": "22:52"
    },
    {
      "time": "22:59"
    },
    {
      "time": "23:06"
    },
    {
      "time": "23:13"
    },
    {
      "time": "23:21"
    },
    {
      "time": "23:30"
    }
  ],
  "legend": [
    "绿色圆点：终点站为巴沟站",
    "红色圆点：终点站为成寿寺站"
  ],
  "warnings": []
}
